intlmc/__init__.py
intlmc/modulo.py
intlmc-0.1.5.dist-info/METADATA
intlmc-0.1.5.dist-info/WHEEL
intlmc-0.1.5.dist-info/top_level.txt
intlmc-0.1.5.dist-info/RECORD
