Metadata-Version: 2.1
Name: intlmc
Version: 0.1.5
Summary: library ML
Author: M Luciano
Author-email: luciano.munoz1@udea.edu.co
License: MIT
Requires-Python: >=3.10.12
Requires-Dist: numpy
